molo.pwa-10.1.1-py3.6-nspkg.pth
molo/pwa/__init__.py
molo/pwa/app_settings.py
molo/pwa/apps.py
molo/pwa/urls.py
molo/pwa/utils.py
molo/pwa/views.py
molo/pwa/templates/fcm.js
molo/pwa/templates/manifest.json
molo/pwa/templates/molo_pwa.html
molo/pwa/templates/serviceworker.js
molo/pwa/templates/toast.min.js
molo/pwa/templatetags/__init__.py
molo/pwa/templatetags/molo_pwa.py
molo/pwa/tests/__init__.py
molo/pwa/tests/test_notifications.py
molo/pwa/tests/test_template_tags.py
molo.pwa-10.1.1.dist-info/LICENSE
molo.pwa-10.1.1.dist-info/METADATA
molo.pwa-10.1.1.dist-info/WHEEL
molo.pwa-10.1.1.dist-info/namespace_packages.txt
molo.pwa-10.1.1.dist-info/top_level.txt
molo.pwa-10.1.1.dist-info/RECORD
