Metadata-Version: 2.1
Name: molo.pwa
Version: 10.1.1
Summary: This is the molo.pwa project.
Home-page: https://github.com/praekelt/molo.pwa
Author: Praekelt Foundation
Author-email: dev@praekeltfoundation.org
License: BSD
Keywords: molo.pwa
Platform: UNKNOWN
Classifier: Intended Audience :: Developers
Classifier: Natural Language :: English
Classifier: Programming Language :: Python :: 3.6
Requires-Dist: molo.core (<11.0.0,>=10.0.0)
Requires-Dist: celery (<4.0)
Requires-Dist: django-celery
Requires-Dist: psycopg2
Requires-Dist: html5lib (==0.9999999)
Requires-Dist: fcm-django
Requires-Dist: Unidecode (==0.04.16)
